sales_report.py
sales_report_annyandr-1.0.dist-info/METADATA
sales_report_annyandr-1.0.dist-info/WHEEL
sales_report_annyandr-1.0.dist-info/entry_points.txt
sales_report_annyandr-1.0.dist-info/top_level.txt
sales_report_annyandr-1.0.dist-info/RECORD
