Metadata-Version: 2.1
Name: sales_report_annyandr
Version: 1.0
Requires-Python: >=3.8
Requires-Dist: pandas
